Metadata-Version: 1.0
Name: bgprob-distributions
Version: 0.1
Summary: Gaussian and Binomila distributions
Home-page: UNKNOWN
Author: Vinit Kumar
Author-email: vinit_kumarin@yahoo.com
License: UNKNOWN
Platform: UNKNOWN
